jaklas/__about__.py
jaklas/__init__.py
jaklas/header.py
jaklas/point_formats.py
jaklas/read.py
jaklas/utils.py
jaklas/write.py
jaklas-0.4.4.dist-info/METADATA
jaklas-0.4.4.dist-info/WHEEL
jaklas-0.4.4.dist-info/top_level.txt
jaklas-0.4.4.dist-info/RECORD
