Metadata-Version: 2.1
Name: jaklas
Version: 0.4.4
Summary: Point cloud writer to las file.
Home-page: https://github.com/jakarto3d/jaklas
Author: Arnaud Venet
Author-email: arnaud.venet@jakarto.com
License: Jakarto Licence
Requires-Python: >=3.6
Requires-Dist: numpy
Requires-Dist: pyproj
Requires-Dist: laspy[lazrs] (>=2.0.0)
